mortar/__init__.py
mortar/proxy.py
mortar/typemap.py
mortar/util.py
dataclass_mortar-0.1.4.dist-info/LICENSE
dataclass_mortar-0.1.4.dist-info/METADATA
dataclass_mortar-0.1.4.dist-info/WHEEL
dataclass_mortar-0.1.4.dist-info/top_level.txt
dataclass_mortar-0.1.4.dist-info/RECORD
