Metadata-Version: 2.1
Name: dataclass-mortar
Version: 0.1.4
Summary: Use dataclasses with SQLAlchemy naturally
Home-page: https://gitlab.com/the203/mortar
Author: Adam Haskell
Author-email: adam@the203.info
License: MIT
Platform: UNKNOWN
Classifier: License :: OSI Approved :: MIT License
Classifier: Programming Language :: Python
Classifier: Programming Language :: Python :: 3
Classifier: Programming Language :: Python :: 3.6
Classifier: Programming Language :: Python :: Implementation :: CPython
Classifier: Programming Language :: Python :: Implementation :: PyPy
Requires-Python: >=3.6.0
